{
  "miniprogramRoot": "./",
  "projectname": "myApp",
  "description": "初遇taro",
  "appid": "wxd4f1d2e053532d9b",
  "setting": {
    "urlCheck": true,
    "es6": true,
    "enhance": true,
    "postcss": false,
    "preloadBackgroundData": false,
    "minified": false,
    "newFeature": true,
    "coverView": true,
    "nodeModules": true,
    "autoAudits": false,
    "showShadowRootInWxmlPanel": true,
    "scopeDataCheck": false,
    "checkInvalidKey": true,
    "checkSiteMap": true,
    "uploadWithSourceMap": true,
    "babelSetting": {
      "ignore": [],
      "disablePlugins": [],
      "outputPath": ""
    },
    "useCompilerModule": false,
    "userConfirmedUseCompilerModuleSwitch": false
  },
  "compileType": "miniprogram",
  "simulatorType": "wechat",
  "simulatorPluginLibVersion": {},
  "libVersion": "2.11.3",
  "condition": {
    "search": {
      "current": -1,
      "list": []
    },
    "conversation": {
      "current": -1,
      "list": []
    },
    "plugin": {
      "current": -1,
      "list": []
    },
    "game": {
      "list": []
    },
    "gamePlugin": {
      "current": -1,
      "list": []
    },
    "miniprogram": {
      "current": -1,
      "list": [
        {
          "id": -1,
          "name": "pages/post/post",
          "pathName": "pages/post/post",
          "query": "",
          "scene": null
        },
        {
          "id": -1,
          "name": "pages/index/index",
          "pathName": "pages/index/index",
          "scene": null
        }
      ]
    }
  }
}